cli/run.py
supernnova/__init__.py
supernnova/conf.py
supernnova/data/__init__.py
supernnova/data/make_dataset.py
supernnova/paper/__init__.py
supernnova/paper/superNNova_metrics.py
supernnova/paper/superNNova_plots.py
supernnova/paper/superNNova_thread.py
supernnova/training/__init__.py
supernnova/training/bayesian_rnn.py
supernnova/training/bayesian_rnn_2.py
supernnova/training/train_rnn.py
supernnova/training/vanilla_rnn.py
supernnova/training/variational_rnn.py
supernnova/utils/__init__.py
supernnova/utils/data_utils.py
supernnova/utils/experiment_settings.py
supernnova/utils/logging_utils.py
supernnova/utils/performance_utils.py
supernnova/utils/swag_utils.py
supernnova/utils/training_utils.py
supernnova/utils/visualization_utils.py
supernnova/validation/__init__.py
supernnova/validation/metrics.py
supernnova/validation/validate_onthefly.py
supernnova/validation/validate_rnn.py
supernnova/visualization/__init__.py
supernnova/visualization/early_prediction.py
supernnova/visualization/prediction_distribution.py
supernnova/visualization/visualize.py
supernnova-3.0.21.dist-info/LICENSE.md
supernnova-3.0.21.dist-info/METADATA
supernnova-3.0.21.dist-info/WHEEL
supernnova-3.0.21.dist-info/entry_points.txt
supernnova-3.0.21.dist-info/RECORD
