Metadata-Version: 2.3
Name: supernnova
Version: 3.0.21
Summary: framework for Bayesian, Neural Network based supernova light-curve classification
License: MIT-expat
Author: Anais Moller
Author-email: amoller@swin.edu.au
Requires-Python: >=3.11,<3.13
Classifier: License :: Other/Proprietary License
Classifier: Programming Language :: Python :: 3
Classifier: Programming Language :: Python :: 3.11
Classifier: Programming Language :: Python :: 3.12
Provides-Extra: dev
Provides-Extra: docs
Requires-Dist: Sphinx (>=6.1.3,<7.0.0) ; extra == "docs"
Requires-Dist: astropy (>=5.3.4,<6.0.0)
Requires-Dist: black (>=22.10,<25.0) ; extra == "dev"
Requires-Dist: click (>=8.1.3,<9.0.0)
Requires-Dist: colorama (>=0.4.6,<0.5.0)
Requires-Dist: h5py (>=3.10.0,<4.0.0)
Requires-Dist: line-profiler (>=4.1.2,<5.0.0) ; extra == "dev"
Requires-Dist: memory-profiler (>=0.61.0,<0.62.0) ; extra == "dev"
Requires-Dist: mlflow (>=2.10.2,<3.0.0)
Requires-Dist: mypy (>=1.1.1,<2.0.0) ; extra == "dev"
Requires-Dist: myst-parser (>=1.0.0,<2.0.0) ; extra == "docs"
Requires-Dist: natsort (>=8.4.0,<9.0.0)
Requires-Dist: pandas (==1.5.1)
Requires-Dist: poetry (>=1.6.1,<2.0.0)
Requires-Dist: pre-commit (>=3.0.4,<4.0.0) ; extra == "dev"
Requires-Dist: pytest (>=7.0,<8.0) ; extra == "dev"
Requires-Dist: pytest-cov (>=4.1.0,<5.0.0) ; extra == "dev"
Requires-Dist: pytest-mock (>=3.11.1,<4.0.0)
Requires-Dist: ruff (>=0.0.243,<0.0.244) ; extra == "dev"
Requires-Dist: scikit-learn (>=1.3.2,<2.0.0)
Requires-Dist: seaborn (>=0.13.0,<0.14.0)
Requires-Dist: sphinx-copybutton (>=0.5.1,<0.6.0) ; extra == "docs"
Requires-Dist: sphinx-rtd-theme (==1.2.0) ; extra == "docs"
Requires-Dist: tabulate (>=0.9.0,<0.10.0)
Requires-Dist: tqdm (>=4.66.1,<5.0.0)
Project-URL: Documentation, https://supernnova.readthedocs.io/en/latest/
Project-URL: Homepage, https://github.com/supernnova/SuperNNova
